yhdiste.py
django_yhdiste-0.3.dist-info/METADATA
django_yhdiste-0.3.dist-info/WHEEL
django_yhdiste-0.3.dist-info/historia.json
django_yhdiste-0.3.dist-info/top_level.txt
django_yhdiste-0.3.dist-info/RECORD
