Metadata-Version: 2.4
Name: django-yhdiste
Version: 0.3
Summary: Django-yhdistenäkymä
Author-email: Antti Hautaniemi <antti.hautaniemi@pispalanit.fi>
Project-URL: Repository, https://github.com/an7oine/django-yhdiste.git
Requires-Python: >=3.8
